yoti-2.14.5.dist-info/licenses/LICENSE.md
yoti_python_sdk/__init__.py
yoti_python_sdk/activity_details.py
yoti_python_sdk/age_verification.py
yoti_python_sdk/aml.py
yoti_python_sdk/anchor.py
yoti_python_sdk/attribute.py
yoti_python_sdk/attribute_issuance_details.py
yoti_python_sdk/attribute_parser.py
yoti_python_sdk/client.py
yoti_python_sdk/config.py
yoti_python_sdk/crypto.py
yoti_python_sdk/date_parser.py
yoti_python_sdk/document_details.py
yoti_python_sdk/endpoint.py
yoti_python_sdk/exceptions.py
yoti_python_sdk/http.py
yoti_python_sdk/image.py
yoti_python_sdk/multivalue.py
yoti_python_sdk/profile.py
yoti_python_sdk/utils.py
yoti_python_sdk/version.py
yoti_python_sdk/doc_scan/__init__.py
yoti_python_sdk/doc_scan/client.py
yoti_python_sdk/doc_scan/constants.py
yoti_python_sdk/doc_scan/endpoint.py
yoti_python_sdk/doc_scan/exception/__init__.py
yoti_python_sdk/doc_scan/exception/doc_scan_exception.py
yoti_python_sdk/doc_scan/session/__init__.py
yoti_python_sdk/doc_scan/session/create/__init__.py
yoti_python_sdk/doc_scan/session/create/notification_config.py
yoti_python_sdk/doc_scan/session/create/sdk_config.py
yoti_python_sdk/doc_scan/session/create/session_spec.py
yoti_python_sdk/doc_scan/session/create/check/__init__.py
yoti_python_sdk/doc_scan/session/create/check/document_authenticity.py
yoti_python_sdk/doc_scan/session/create/check/document_comparison.py
yoti_python_sdk/doc_scan/session/create/check/face_match.py
yoti_python_sdk/doc_scan/session/create/check/liveness.py
yoti_python_sdk/doc_scan/session/create/check/requested_check.py
yoti_python_sdk/doc_scan/session/create/check/watchlist_screen.py
yoti_python_sdk/doc_scan/session/create/filter/__init__.py
yoti_python_sdk/doc_scan/session/create/filter/document_filter.py
yoti_python_sdk/doc_scan/session/create/filter/document_restrictions_filter.py
yoti_python_sdk/doc_scan/session/create/filter/orthogonal_restrictions_filter.py
yoti_python_sdk/doc_scan/session/create/filter/required_document.py
yoti-2.14.5.dist-info/METADATA
yoti-2.14.5.dist-info/WHEEL
yoti-2.14.5.dist-info/top_level.txt
yoti-2.14.5.dist-info/RECORD
