Metadata-Version: 2.4
Name: yoti
Version: 2.14.5
Summary: The Yoti Python SDK, providing API support for Login, Verify (2FA) and Age Verification.
Home-page: https://github.com/getyoti/yoti-python-sdk
Author: Yoti
Author-email: websdk@yoti.com
License: MIT
Keywords: yoti sdk 2FA multifactor authentication verification identity login register verify 2Factor
Classifier: Development Status :: 5 - Production/Stable
Classifier: License :: OSI Approved :: MIT License
Classifier: Operating System :: OS Independent
Classifier: Intended Audience :: Developers
Classifier: Programming Language :: Python
Classifier: Programming Language :: Python :: 3.9
Classifier: Programming Language :: Python :: 3.10
Classifier: Programming Language :: Python :: 3.11
Classifier: Programming Language :: Python :: 3.12
Classifier: Topic :: Software Development :: Libraries :: Python Modules
Requires-Python: >=3.9
License-File: LICENSE.md
Requires-Dist: asn1==2.2.0
Requires-Dist: cryptography>=42.0.0
Requires-Dist: protobuf>=4.21.12
Requires-Dist: requests>=2.31.0
Requires-Dist: pyopenssl>=24.0.0
Requires-Dist: pytz>=2025.2
Requires-Dist: iso8601>=1.1.0
Requires-Dist: deprecated>=1.2.14
Provides-Extra: examples
Requires-Dist: Django>=3.0.7; extra == "examples"
Requires-Dist: Flask>=1.0.4; extra == "examples"
Requires-Dist: python-dotenv>=0.7.1; extra == "examples"
Requires-Dist: django-sslserver>=0.22.0; extra == "examples"
Requires-Dist: Werkzeug==2.1.2; extra == "examples"
Provides-Extra: dev
Requires-Dist: pre-commit==2.16.0; extra == "dev"
Requires-Dist: pytest>=4.6.11; extra == "dev"
Requires-Dist: pytest-cov>=2.7.1; extra == "dev"
Requires-Dist: pylint==1.9.4; extra == "dev"
Requires-Dist: pylint-exit>=1.1.0; extra == "dev"
Requires-Dist: python-coveralls==2.9.3; extra == "dev"
Requires-Dist: coverage>=7.4.0; extra == "dev"
Requires-Dist: mock==2.0.0; extra == "dev"
Requires-Dist: virtualenv==20.15.1; extra == "dev"
Requires-Dist: flake8==4.0.1; extra == "dev"
Requires-Dist: pip-tools==6.6.2; extra == "dev"
Dynamic: author
Dynamic: author-email
Dynamic: classifier
Dynamic: description
Dynamic: description-content-type
Dynamic: home-page
Dynamic: keywords
Dynamic: license
Dynamic: license-file
Dynamic: provides-extra
Dynamic: requires-dist
Dynamic: requires-python
Dynamic: summary
